{"article": {"id": "Immigration1.0-33155", "title": "DeKalb; DeKalb"}, "title_result": "\n                                                                                    A 2nd Chance Bail Bonds Celebrates the One-Year Anniversary of its DeKalb Office;The office in DeKalb County has performed exceptionally well, becoming a bail bond agency of choice in the area\n                                                                                ", "title_match": false, "downloaded": true, "found": true}