{"article": {"id": "Immigration1.0-17126", "title": "The reheating of immigration reform"}, "title_result": "\n                                                                                    Progressives for Immigration Reform Says Trump Administration Should 'Make America Green Again' by Utilizing Environmental Law;NEPA can be applied to look at impact of population growth on the environment\n                                                                                ", "title_match": false, "downloaded": true, "found": true}